vjepa/__init__.py
vjepa/datasets/__init__.py
vjepa/datasets/data_manager.py
vjepa/datasets/image_dataset.py
vjepa/datasets/utils/__init__.py
vjepa/datasets/utils/video/__init__.py
vjepa/datasets/utils/video/functional.py
vjepa/datasets/utils/video/randaugment.py
vjepa/datasets/utils/video/randerase.py
vjepa/datasets/utils/video/transforms.py
vjepa/datasets/utils/video/volume_transforms.py
vjepa/datasets/utils/weighted_sampler.py
vjepa/datasets/video_dataset.py
vjepa/masks/__init__.py
vjepa/masks/default.py
vjepa/masks/multiblock3d.py
vjepa/masks/random_tube.py
vjepa/masks/utils.py
vjepa/models/__init__.py
vjepa/models/attentive_pooler.py
vjepa/models/predictor.py
vjepa/models/utils/__init__.py
vjepa/models/utils/modules.py
vjepa/models/utils/multimask.py
vjepa/models/utils/patch_embed.py
vjepa/models/utils/pos_embs.py
vjepa/models/vision_transformer.py
vjepa/utils/__init__.py
vjepa/utils/distributed.py
vjepa/utils/logging.py
vjepa/utils/monitoring.py
vjepa/utils/schedulers.py
vjepa/utils/tensors.py
vjepa/version.py
vjepa-0.1.2.dist-info/LICENSE
vjepa-0.1.2.dist-info/METADATA
vjepa-0.1.2.dist-info/WHEEL
vjepa-0.1.2.dist-info/RECORD
