Metadata-Version: 2.1
Name: vjepa
Version: 0.1.2
Summary: Moedified from the official PyTorch codebase for the video joint-embedding predictive architecture, V-JEPA, a method for self-supervised learning of visual representations from video.
Author: Adrien Bardes
Author-email: abardes@meta.com
Requires-Python: >=3.9,<4.0
Classifier: Programming Language :: Python :: 3
Classifier: Programming Language :: Python :: 3.9
Classifier: Programming Language :: Python :: 3.10
Classifier: Programming Language :: Python :: 3.11
Classifier: Programming Language :: Python :: 3.12
Requires-Dist: beartype (>=0.19.0,<0.20.0)
Requires-Dist: braceexpand (>=0.1.7,<0.2.0)
Requires-Dist: decord (>=0.6.0,<0.7.0)
Requires-Dist: einops (>=0.8.0,<0.9.0)
Requires-Dist: numpy (>=1.24.0)
Requires-Dist: opencv-python (>=4.10.0.84,<5.0.0.0)
Requires-Dist: pandas (==2.2.2)
Requires-Dist: pyyaml (>=6.0.2,<7.0.0)
Requires-Dist: submitit (>=1.5.2,<2.0.0)
Requires-Dist: timm (>=1.0.9,<2.0.0)
Requires-Dist: torch (>=2)
Requires-Dist: torchvision (>=0.19.1,<0.20.0)
Requires-Dist: webdataset (>=0.2.100,<0.3.0)
